anls/__init__.py
anls/cli/__init__.py
anls/cli/args.py
anls/cli/run.py
anls/common/__init__.py
anls/common/exception.py
anls/common/util.py
anls/evaluation/__init__.py
anls/evaluation/const.py
anls/evaluation/display_results.py
anls/evaluation/evaluate_json.py
anls/evaluation/schema.py
anls/evaluation/validate_data.py
anls/metrics/__init__.py
anls/metrics/dist.py
anls/metrics/score.py
anls-0.0.2.dist-info/entry_points.txt
anls-0.0.2.dist-info/LICENSE
anls-0.0.2.dist-info/WHEEL
anls-0.0.2.dist-info/METADATA
anls-0.0.2.dist-info/RECORD
