Metadata-Version: 2.1
Name: anls
Version: 0.0.2
Summary: ANLS: Average Normalized Levenshtein Similarity
Home-page: https://github.com/shunk031/ANLS
License: MIT
Author: Shunsuke KITADA
Author-email: shunsuke.kitada.0831@gmail.com
Requires-Python: >=3.7,<4.0
Classifier: License :: OSI Approved :: MIT License
Classifier: Programming Language :: Python :: 3
Classifier: Programming Language :: Python :: 3.10
Classifier: Programming Language :: Python :: 3.7
Classifier: Programming Language :: Python :: 3.8
Classifier: Programming Language :: Python :: 3.9
Project-URL: Repository, https://github.com/shunk031/ANLS
